{
  "grade": "四年级上册",
  "subject": "数学",
  "version": "人教版",
  "total_sections": 9,
  "sections": [
    {
      "id": 1,
      "title": "大数的认识",
      "description": "认识万以上的数，掌握计数单位、数位、数级，能读写大数，会比较大小，会改写和求近似数，认识计算器",
      "subsections": [
        {
          "title": "亿以内数的认识",
          "kps": [
            "计数单位：个、十、百、千、万、十万、百万、千万、亿",
            "每相邻两个计数单位间的进率是10",
            "数位：个位~千万位，建立数位顺序表",
            "数级：个级、万级、亿级，每4个数位一级"
          ],
          "concepts": [
            "计数单位",
            "数位",
            "数级",
            "十进制"
          ],
          "difficulty": "基础",
          "weight": "高"
        },
        {
          "title": "亿以内数的读法",
          "kps": [
            "先读万级再读个级，万级加万字",
            "每级末尾0不读，中间连续几个0只读一个"
          ],
          "concepts": [
            "分级读法",
            "0的读法"
          ],
          "difficulty": "基础",
          "weight": "高"
        },
        {
          "title": "亿以内数的写法",
          "kps": [
            "先写万级再写个级",
            "哪一位上一个单位也没有就写0占位"
          ],
          "concepts": [
            "分级写法",
            "0占位"
          ],
          "difficulty": "基础",
          "weight": "高"
        },
        {
          "title": "比较数的大小",
          "kps": [
            "位数不同则位数多的数大",
            "位数相同则从高位逐位比"
          ],
          "concepts": [
            "比较法则"
          ],
          "difficulty": "基础",
          "weight": "中"
        },
        {
          "title": "数的改写",
          "kps": [
            "整万数去掉末尾4个0加万字",
            "整亿数去掉末尾8个0加亿字"
          ],
          "concepts": [
            "改写方法"
          ],
          "difficulty": "基础",
          "weight": "中"
        },
        {
          "title": "近似数（四舍五入）",
          "kps": [
            "省略万位后的尾数：看千位四舍五入",
            "省略亿位后的尾数：看千万位四舍五入",
            "准确数与近似数的区别"
          ],
          "concepts": [
            "四舍五入",
            "近似数"
          ],
          "difficulty": "中等",
          "weight": "高"
        },
        {
          "title": "亿以上数的认识",
          "kps": [
            "亿以上数的读写方法同亿以内数",
            "改写和求近似数方法同上"
          ],
          "concepts": [
            "亿以上数"
          ],
          "difficulty": "中等",
          "weight": "中"
        },
        {
          "title": "计算器的认识和使用",
          "kps": [
            "ON/C、OFF、数字键、运算键、等号键",
            "用计算器进行大数运算和探索规律"
          ],
          "concepts": [
            "计算器"
          ],
          "difficulty": "基础",
          "weight": "低"
        }
      ]
    },
    {
      "id": 2,
      "title": "公顷和平方千米",
      "description": "认识公顷和平方千米两个大面积单位及换算",
      "subsections": [
        {
          "title": "公顷",
          "kps": [
            "边长100米的正方形面积=1公顷=10000平方米"
          ],
          "concepts": [
            "公顷"
          ],
          "difficulty": "基础",
          "weight": "高"
        },
        {
          "title": "平方千米",
          "kps": [
            "边长1000米的正方形面积=1平方千米=1000000平方米",
            "1平方千米=100公顷"
          ],
          "concepts": [
            "平方千米",
            "面积单位换算"
          ],
          "difficulty": "基础",
          "weight": "高"
        }
      ]
    },
    {
      "id": 3,
      "title": "角的度量",
      "description": "认识线段射线直线，理解角，会度量、分类和画角",
      "subsections": [
        {
          "title": "线段、射线、直线",
          "kps": [
            "线段：2端点，可度量；射线：1端点，无限长；直线：0端点，无限长",
            "过一点无数条直线，过两点一条直线"
          ],
          "concepts": [
            "线段",
            "射线",
            "直线"
          ],
          "difficulty": "基础",
          "weight": "中"
        },
        {
          "title": "角的认识和度量",
          "kps": [
            "角：由一点引出两条射线，角的大小与两边叉开程度有关",
            "量角器使用：中心对顶点、0刻度对一边、读另一边刻度",
            "度量单位：度（°）"
          ],
          "concepts": [
            "角",
            "量角器"
          ],
          "difficulty": "基础",
          "weight": "高"
        },
        {
          "title": "角的分类",
          "kps": [
            "锐角<90°<钝角<180°，直角=90°，平角=180°，周角=360°",
            "1周角=2平角=4直角"
          ],
          "concepts": [
            "锐角",
            "直角",
            "钝角",
            "平角",
            "周角"
          ],
          "difficulty": "基础",
          "weight": "高"
        },
        {
          "title": "画角",
          "kps": [
            "用量角器画指定度数：射线→中心对齐→找刻度→连线",
            "三角尺画30°、45°、60°、90°特殊角"
          ],
          "concepts": [
            "画角"
          ],
          "difficulty": "中等",
          "weight": "中"
        }
      ]
    },
    {
      "id": 4,
      "title": "三位数乘两位数",
      "description": "掌握笔算方法、速度×时间=路程和积的变化规律",
      "subsections": [
        {
          "title": "笔算乘法",
          "kps": [
            "个位乘三位的积对齐个位，十位乘三位的积对齐十位",
            "两次积相加，因数末尾有0的简便算法"
          ],
          "concepts": [
            "笔算"
          ],
          "difficulty": "中等",
          "weight": "高"
        },
        {
          "title": "速度×时间=路程",
          "kps": [
            "速度×时间=路程，路程÷时间=速度，路程÷速度=时间",
            "速度的表示：千米/时、米/分"
          ],
          "concepts": [
            "速度",
            "路程",
            "时间"
          ],
          "difficulty": "中等",
          "weight": "高"
        },
        {
          "title": "积的变化规律",
          "kps": [
            "一个因数不变，另一因数乘几，积也乘几",
            "一个因数不变，另一因数除以几，积也除以几"
          ],
          "concepts": [
            "积的变化"
          ],
          "difficulty": "中等",
          "weight": "中"
        }
      ]
    },
    {
      "id": 5,
      "title": "平行四边形和梯形",
      "description": "认识平行与垂直、平行四边形和梯形的特征",
      "subsections": [
        {
          "title": "平行与垂直",
          "kps": [
            "平行：同一平面内不相交的两条直线",
            "垂直：相交成直角的两条直线",
            "点到直线的距离：垂直线段最短",
            "平行线间的距离处处相等"
          ],
          "concepts": [
            "平行",
            "垂直",
            "距离"
          ],
          "difficulty": "中等",
          "weight": "高"
        },
        {
          "title": "平行四边形",
          "kps": [
            "两组对边分别平行且相等，对角相等",
            "不稳定性（容易变形）",
            "底和高的概念"
          ],
          "concepts": [
            "平行四边形",
            "底",
            "高"
          ],
          "difficulty": "中等",
          "weight": "高"
        },
        {
          "title": "梯形",
          "kps": [
            "只有一组对边平行：上底、下底、腰、高",
            "等腰梯形：两腰相等",
            "直角梯形：有一个直角"
          ],
          "concepts": [
            "梯形",
            "等腰梯形",
            "直角梯形"
          ],
          "difficulty": "中等",
          "weight": "高"
        }
      ]
    },
    {
      "id": 6,
      "title": "除数是两位数的除法",
      "description": "掌握口算和笔算除法，理解商的变化规律",
      "subsections": [
        {
          "title": "口算除法",
          "kps": [
            "几十/几百几十除以整十数：用表内除法类推",
            "例：80÷20=4，150÷30=5"
          ],
          "concepts": [
            "口算"
          ],
          "difficulty": "基础",
          "weight": "中"
        },
        {
          "title": "笔算除法（整十数除）",
          "kps": [
            "看被除数前两位，不够除看三位",
            "商写在个位，余数小于除数"
          ],
          "concepts": [
            "笔算",
            "试商"
          ],
          "difficulty": "中等",
          "weight": "高"
        },
        {
          "title": "笔算除法（非整十数——四舍五入试商）",
          "kps": [
            "四舍法试商：除数看小→初商可能偏大→调小",
            "五入法试商：除数看大→初商可能偏小→调大",
            "验算：商×除数+余数=被除数"
          ],
          "concepts": [
            "四舍试商",
            "五入试商",
            "调商",
            "验算"
          ],
          "difficulty": "较难",
          "weight": "高"
        },
        {
          "title": "商的变化规律",
          "kps": [
            "除数不变，被除数乘几商乘几",
            "被除数不变，除数乘几商反而除以几",
            "被除数和除数同时乘/除以相同非0数，商不变"
          ],
          "concepts": [
            "商的变化",
            "商不变"
          ],
          "difficulty": "中等",
          "weight": "中"
        }
      ]
    },
    {
      "id": 7,
      "title": "条形统计图",
      "description": "认识条形统计图，用1格表示多个单位",
      "subsections": [
        {
          "title": "条形统计图的绘制与分析",
          "kps": [
            "直条高低表示数据多少",
            "1格可表示1个或多个单位（根据数据范围合理选择）",
            "从图中获取最大/最小/趋势信息"
          ],
          "concepts": [
            "条形图",
            "数据分析"
          ],
          "difficulty": "基础",
          "weight": "中"
        }
      ]
    },
    {
      "id": 8,
      "title": "数学广角—优化",
      "description": "用优化思想解决实际问题",
      "subsections": [
        {
          "title": "沏茶问题",
          "kps": [
            "能同时做的事同时做节约时间"
          ],
          "concepts": [
            "顺序优化"
          ],
          "difficulty": "中等",
          "weight": "中"
        },
        {
          "title": "烙饼问题",
          "kps": [
            "每次最多2张饼、两面都烙",
            "3张饼最少9分钟（交替烙法）"
          ],
          "concepts": [
            "资源优化"
          ],
          "difficulty": "中等",
          "weight": "中"
        },
        {
          "title": "田忌赛马（策略）",
          "kps": [
            "以弱对强：用最弱的对对方最强的",
            "有序思考所有方案再选最优"
          ],
          "concepts": [
            "策略优化"
          ],
          "difficulty": "较难",
          "weight": "中"
        }
      ]
    },
    {
      "id": 9,
      "title": "总复习",
      "description": "全册综合复习",
      "subsections": [
        {
          "title": "数与计算复习",
          "kps": [
            "大数、乘法、除法综合复习"
          ],
          "concepts": [
            "综合"
          ],
          "difficulty": "中等",
          "weight": "中"
        },
        {
          "title": "图形与几何复习",
          "kps": [
            "公顷/平方千米、角、平行四边形和梯形复习"
          ],
          "concepts": [
            "综合"
          ],
          "difficulty": "中等",
          "weight": "中"
        },
        {
          "title": "统计与优化复习",
          "kps": [
            "条形统计图、优化问题复习"
          ],
          "concepts": [
            "综合"
          ],
          "difficulty": "中等",
          "weight": "中"
        }
      ]
    }
  ]
}