[
  {
    "id": "D_S1_001",
    "type": "口算",
    "chapter": 1,
    "kp": "加、减法的意义",
    "diff": "基础",
    "q": "根据2468+575=3043，直接写出3043-2468=____",
    "ans": "575",
    "exp": "加法各部分间的关系。",
    "t": "15秒"
  },
  {
    "id": "D_S1_002",
    "type": "口算",
    "chapter": 1,
    "kp": "加、减法的意义",
    "diff": "基础",
    "q": "把两个数合并成一个数的运算，叫作____。",
    "ans": "加法",
    "exp": "加法的定义。",
    "t": "10秒"
  },
  {
    "id": "D_S1_003",
    "type": "填空题",
    "chapter": 1,
    "kp": "加、减法的意义",
    "diff": "基础",
    "q": "已知两个加数的和与其中一个加数，求另一个加数的运算，叫作____，它是____的逆运算。",
    "ans": "减法；加法",
    "exp": "减法的定义。",
    "t": "15秒"
  },
  {
    "id": "D_S1_004",
    "type": "口算",
    "chapter": 1,
    "kp": "乘、除法的意义",
    "diff": "基础",
    "q": "求几个相同加数的和的简便运算，叫作____。",
    "ans": "乘法",
    "exp": "乘法的定义。",
    "t": "10秒"
  },
  {
    "id": "D_S1_005",
    "type": "口算",
    "chapter": 1,
    "kp": "乘、除法的意义",
    "diff": "基础",
    "q": "已知两个因数的积与其中一个因数，求另一个因数的运算，叫作____。",
    "ans": "除法",
    "exp": "除法的定义。",
    "t": "10秒"
  },
  {
    "id": "D_S1_006",
    "type": "填空题",
    "chapter": 1,
    "kp": "乘、除法的意义",
    "diff": "基础",
    "q": "除数是乘法的____运算。",
    "ans": "逆",
    "exp": "除法是乘法的逆运算。",
    "t": "10秒"
  },
  {
    "id": "D_S1_007",
    "type": "口算",
    "chapter": 1,
    "kp": "加、减法的意义",
    "diff": "基础",
    "q": "根据36×14=504，直接写出504÷14=____，504÷36=____",
    "ans": "36；14",
    "exp": "乘除法各部分间的关系。",
    "t": "15秒"
  },
  {
    "id": "D_S1_008",
    "type": "口算",
    "chapter": 1,
    "kp": "加、减法的意义",
    "diff": "基础",
    "q": "在加法中，加数+加数=____；在减法中，被减数-减数=____。",
    "ans": "和；差",
    "exp": "加法减法各部分名称。",
    "t": "10秒"
  },
  {
    "id": "D_S1_009",
    "type": "填空题",
    "chapter": 1,
    "kp": "加、减法的意义",
    "diff": "基础",
    "q": "根据850-239=611，写出另外两个算式：____和____。",
    "ans": "850-611=239；239+611=850",
    "exp": "加减法各部分间的关系。",
    "t": "20秒"
  },
  {
    "id": "D_S1_010",
    "type": "选择题",
    "chapter": 1,
    "kp": "加、减法的意义",
    "diff": "基础",
    "q": "下面哪个算式不能表示减法的意义？",
    "opts": [
      "A.已知和求加数",
      "B.已知差求被减数",
      "C.已知两个数的和与一个加数求另一个",
      "D.求几个相同加数的和"
    ],
    "ans": "D",
    "exp": "D是乘法的定义。",
    "t": "15秒"
  },
  {
    "id": "D_S1_011",
    "type": "口算",
    "chapter": 1,
    "kp": "乘、除法的意义",
    "diff": "基础",
    "q": "相乘的两个数叫作____，乘得的数叫作____。",
    "ans": "因数；积",
    "exp": "乘法各部分名称。",
    "t": "10秒"
  },
  {
    "id": "D_S1_012",
    "type": "口算",
    "chapter": 1,
    "kp": "乘、除法的意义",
    "diff": "基础",
    "q": "被除数÷除数=____，除法中余数____除数（填>、<或=）。",
    "ans": "商；<",
    "exp": "余数必须小于除数。",
    "t": "10秒"
  },
  {
    "id": "D_S1_013",
    "type": "口算",
    "chapter": 1,
    "kp": "乘、除法的意义",
    "diff": "基础",
    "q": "在有余数的除法中，被除数=____×____+____。",
    "ans": "商；除数；余数",
    "exp": "有余数除法的验算方法。",
    "t": "15秒"
  },
  {
    "id": "D_S1_014",
    "type": "填空题",
    "chapter": 1,
    "kp": "0的运算",
    "diff": "基础",
    "q": "一个数加上0，还得____；一个数减去0，还得____。",
    "ans": "原数；原数",
    "exp": "0的加减特性。",
    "t": "10秒"
  },
  {
    "id": "D_S1_015",
    "type": "填空题",
    "chapter": 1,
    "kp": "0的运算",
    "diff": "基础",
    "q": "被减数等于减数时，差是____；一个数乘0，得____。",
    "ans": "0；0",
    "exp": "0的运算特性。",
    "t": "10秒"
  },
  {
    "id": "D_S1_016",
    "type": "填空题",
    "chapter": 1,
    "kp": "0的运算",
    "diff": "基础",
    "q": "0除以____，还得0；____不能作除数。",
    "ans": "一个非0的数；0",
    "exp": "关于0的除法规则。",
    "t": "10秒"
  },
  {
    "id": "D_S1_017",
    "type": "口算",
    "chapter": 1,
    "kp": "0的运算",
    "diff": "基础",
    "q": "0+5=____，0×5=____，0÷5=____",
    "ans": "5；0；0",
    "exp": "0的运算练习。",
    "t": "10秒"
  },
  {
    "id": "D_S1_018",
    "type": "口算",
    "chapter": 1,
    "kp": "四则混合运算",
    "diff": "基础",
    "q": "计算：15+25×3=？",
    "ans": "90",
    "exp": "先乘后加：25×3=75, 15+75=90。",
    "t": "20秒"
  },
  {
    "id": "D_S1_019",
    "type": "口算",
    "chapter": 1,
    "kp": "四则混合运算",
    "diff": "基础",
    "q": "计算：(15+25)×3=？",
    "ans": "120",
    "exp": "先算括号：40×3=120。",
    "t": "20秒"
  },
  {
    "id": "D_S1_020",
    "type": "选择题",
    "chapter": 1,
    "kp": "四则混合运算",
    "diff": "基础",
    "q": "在没有括号的算式里，有乘、除法和加、减法，要（ ）。",
    "opts": [
      "A.从左到右算",
      "B.先算乘除后算加减",
      "C.先算加减后算乘除",
      "D.从右到左算"
    ],
    "ans": "B",
    "exp": "先乘除后加减。",
    "t": "15秒"
  },
  {
    "id": "D_S1_021",
    "type": "口算",
    "chapter": 1,
    "kp": "四则混合运算",
    "diff": "中等",
    "q": "计算：96÷12+4×2=？",
    "ans": "16",
    "exp": "96÷12=8, 4×2=8, 8+8=16。",
    "t": "25秒"
  },
  {
    "id": "D_S1_022",
    "type": "口算",
    "chapter": 1,
    "kp": "四则混合运算",
    "diff": "中等",
    "q": "计算：50×(2+4)-59=？",
    "ans": "241",
    "exp": "先括号：2+4=6, 50×6=300, 300-59=241。",
    "t": "25秒"
  },
  {
    "id": "D_S1_023",
    "type": "填空题",
    "chapter": 1,
    "kp": "四则混合运算",
    "diff": "中等",
    "q": "在算式60-30÷5×2=中，应先算____法，再算____法，最后算____法。",
    "ans": "除；乘；减",
    "exp": "先算30÷5=6, 再算6×2=12, 最后60-12=48。",
    "t": "20秒"
  },
  {
    "id": "D_S1_024",
    "type": "应用题",
    "chapter": 1,
    "kp": "四则混合运算",
    "diff": "中等",
    "q": "商店运来苹果125千克，运来的梨比苹果的3倍少50千克。运来梨多少千克？",
    "ans": "325千克",
    "exp": "125×3-50=375-50=325。",
    "t": "25秒"
  },
  {
    "id": "D_S1_025",
    "type": "应用题",
    "chapter": 1,
    "kp": "加、减法的意义",
    "diff": "中等",
    "q": "一根绳子长200米，第一次用去78米，第二次用去65米。还剩多少米？（用两种方法解答）",
    "ans": "57米",
    "exp": "方法一：200-78-65=57；方法二：200-(78+65)=57。",
    "t": "25秒"
  },
  {
    "id": "D_S1_026",
    "type": "口算",
    "chapter": 1,
    "kp": "加、减法的意义",
    "diff": "基础",
    "q": "□+18=37，□=____",
    "ans": "19",
    "exp": "加数=和-另一个加数：37-18=19。",
    "t": "10秒"
  },
  {
    "id": "D_S1_027",
    "type": "口算",
    "chapter": 1,
    "kp": "加、减法的意义",
    "diff": "基础",
    "q": "540-□=210，□=____",
    "ans": "330",
    "exp": "减数=被减数-差：540-210=330。",
    "t": "10秒"
  },
  {
    "id": "D_S1_028",
    "type": "口算",
    "chapter": 1,
    "kp": "乘、除法的意义",
    "diff": "基础",
    "q": "□×18=774，□=____",
    "ans": "43",
    "exp": "因数=积÷另一个因数：774÷18=43。",
    "t": "20秒"
  },
  {
    "id": "D_S1_029",
    "type": "口算",
    "chapter": 1,
    "kp": "四则混合运算",
    "diff": "基础",
    "q": "先说出运算顺序再口算：72-36÷4=？",
    "ans": "63",
    "exp": "先除后减：36÷4=9, 72-9=63。",
    "t": "20秒"
  },
  {
    "id": "D_S1_030",
    "type": "口算",
    "chapter": 1,
    "kp": "四则混合运算",
    "diff": "基础",
    "q": "200+128÷32=？",
    "ans": "204",
    "exp": "128÷32=4, 200+4=204。",
    "t": "20秒"
  },
  {
    "id": "D_S1_031",
    "type": "选择题",
    "chapter": 1,
    "kp": "四则混合运算",
    "diff": "基础",
    "q": "在算式(28+72)×10-50中，最先算的是？",
    "opts": [
      "A.乘法",
      "B.加法",
      "C.减法",
      "D.都可以"
    ],
    "ans": "B",
    "exp": "有括号先算括号内的加法。",
    "t": "15秒"
  },
  {
    "id": "D_S1_032",
    "type": "填空题",
    "chapter": 1,
    "kp": "四则混合运算",
    "diff": "中等",
    "q": "把下面算式写成一个综合算式：48+12=60, 60×5=300 -> 综合算式：____",
    "ans": "(48+12)×5=300",
    "exp": "第一步加法，第二步乘法，加法需加括号。",
    "t": "20秒"
  },
  {
    "id": "D_S1_033",
    "type": "应用题",
    "chapter": 1,
    "kp": "乘、除法的意义",
    "diff": "中等",
    "q": "学校买了6个篮球，每个120元，又买了4个足球，每个95元。一共花了多少钱？",
    "ans": "1100元",
    "exp": "6×120+4×95=720+380=1100。",
    "t": "25秒"
  },
  {
    "id": "D_S1_034",
    "type": "口算",
    "chapter": 1,
    "kp": "四则混合运算",
    "diff": "中等",
    "q": "计算：25×4-25×4=？",
    "ans": "0",
    "exp": "100-100=0。",
    "t": "20秒"
  },
  {
    "id": "D_S1_035",
    "type": "应用题",
    "chapter": 1,
    "kp": "四则混合运算",
    "diff": "提高",
    "q": "学校买来6箱矿泉水，每箱24瓶。每个班级分9瓶，共分给了几个班？还剩几瓶？",
    "ans": "16个班，剩0瓶。",
    "exp": "总瓶数=6×24=144，144÷9=16，正好整除。",
    "t": "25秒"
  },
  {
    "id": "D_S1_036",
    "type": "填空题",
    "chapter": 1,
    "kp": "四则混合运算",
    "diff": "中等",
    "q": "在算式360÷[(12+6)×5]中，应先算____法，再算____法，最后算____法。",
    "ans": "加；乘；除",
    "exp": "先括号内12+6=18，再18×5=90，最后360÷90=4。",
    "t": "25秒"
  },
  {
    "id": "D_S1_037",
    "type": "口算",
    "chapter": 1,
    "kp": "加、减法的意义",
    "diff": "基础",
    "q": "根据47-19=28，写出两个算式：28+19=47，____。",
    "ans": "47-28=19",
    "exp": "加减法互逆关系。",
    "t": "15秒"
  },
  {
    "id": "D_S1_038",
    "type": "口算",
    "chapter": 1,
    "kp": "乘、除法的意义",
    "diff": "基础",
    "q": "根据714÷17=42，写出两个算式：____和____。",
    "ans": "17×42=714；714÷42=17",
    "exp": "乘除法互逆关系。",
    "t": "15秒"
  },
  {
    "id": "D_S1_039",
    "type": "口算",
    "chapter": 1,
    "kp": "四则混合运算",
    "diff": "中等",
    "q": "计算：78+78×0+78÷78=？",
    "ans": "79",
    "exp": "78×0=0，78÷78=1，78+0+1=79。",
    "t": "25秒"
  },
  {
    "id": "D_S1_040",
    "type": "应用题",
    "chapter": 1,
    "kp": "四则混合运算",
    "diff": "提高",
    "q": "36名同学去公园划船。大船每条坐6人，小船每条坐4人。如果每条船都坐满，怎样租船能使所有同学同时上船？写出两种方案。",
    "ans": "方案一：6条大船；方案二：4条大船3条小船",
    "exp": "6×6=36；4×6+3×4=24+12=36。",
    "t": "40秒"
  },
  {
    "id": "D_S3_001",
    "type": "填空题",
    "chapter": 3,
    "kp": "加法运算律",
    "diff": "基础",
    "q": "两个数相加，交换加数的位置，和不变，这叫做____。用字母表示为____。",
    "ans": "加法交换律；a+b=b+a",
    "exp": "加法交换律的定义和公式。",
    "t": "15秒"
  },
  {
    "id": "D_S3_002",
    "type": "填空题",
    "chapter": 3,
    "kp": "加法运算律",
    "diff": "基础",
    "q": "三个数相加，先把前两个数相加，或者先把后两个数相加，和不变，这叫做____。用字母表示为____。",
    "ans": "加法结合律；(a+b)+c=a+(b+c)",
    "exp": "加法结合律的定义和公式。",
    "t": "15秒"
  },
  {
    "id": "D_S3_003",
    "type": "口算",
    "chapter": 3,
    "kp": "加法运算律",
    "diff": "基础",
    "q": "运用加法交换律填空：56+78=78+____",
    "ans": "56",
    "exp": "加法交换律。",
    "t": "10秒"
  },
  {
    "id": "D_S3_004",
    "type": "口算",
    "chapter": 3,
    "kp": "加法运算律",
    "diff": "基础",
    "q": "运用加法结合律填空：(25+68)+32=25+(____+____)",
    "ans": "68；32",
    "exp": "加法结合律。",
    "t": "10秒"
  },
  {
    "id": "D_S3_005",
    "type": "口算",
    "chapter": 3,
    "kp": "加法运算律",
    "diff": "基础",
    "q": "计算：88+57+12=？运用运算律简便计算。",
    "ans": "157",
    "exp": "88+12+57=100+57=157。",
    "t": "20秒"
  },
  {
    "id": "D_S3_006",
    "type": "填空题",
    "chapter": 3,
    "kp": "乘法运算律",
    "diff": "基础",
    "q": "两个数相乘，交换因数的位置，积不变。这叫做____。字母公式：____。",
    "ans": "乘法交换律；a×b=b×a",
    "exp": "乘法交换律。",
    "t": "15秒"
  },
  {
    "id": "D_S3_007",
    "type": "填空题",
    "chapter": 3,
    "kp": "乘法运算律",
    "diff": "基础",
    "q": "三个数相乘，先把前两个数相乘，或者先把后两个数相乘，积不变。这叫做____。字母公式：____。",
    "ans": "乘法结合律；(a×b)×c=a×(b×c)",
    "exp": "乘法结合律。",
    "t": "15秒"
  },
  {
    "id": "D_S3_008",
    "type": "填空题",
    "chapter": 3,
    "kp": "乘法运算律",
    "diff": "中等",
    "q": "两个数的和与一个数相乘，可以先把它们分别与这个数相乘，再相加。这叫做____。字母公式：____。",
    "ans": "乘法分配律；(a+b)×c=a×c+b×c",
    "exp": "乘法分配律的定义和公式。",
    "t": "20秒"
  },
  {
    "id": "D_S3_009",
    "type": "口算",
    "chapter": 3,
    "kp": "乘法运算律",
    "diff": "基础",
    "q": "计算：25×73×4=？(运用运算律)",
    "ans": "7300",
    "exp": "25×4×73=100×73=7300。",
    "t": "20秒"
  },
  {
    "id": "D_S3_010",
    "type": "口算",
    "chapter": 3,
    "kp": "简便计算综合",
    "diff": "基础",
    "q": "计算：125×88=？(简便计算)",
    "ans": "11000",
    "exp": "125×8×11=1000×11=11000(或125×80+125×8=10000+1000=11000)",
    "t": "25秒"
  },
  {
    "id": "D_S3_011",
    "type": "口算",
    "chapter": 3,
    "kp": "简便计算综合",
    "diff": "中等",
    "q": "计算：102×35=？",
    "ans": "3570",
    "exp": "(100+2)×35=100×35+2×35=3500+70=3570。",
    "t": "25秒"
  },
  {
    "id": "D_S3_012",
    "type": "口算",
    "chapter": 3,
    "kp": "简便计算综合",
    "diff": "基础",
    "q": "计算：25+137+75=？",
    "ans": "237",
    "exp": "25+75+137=100+137=237。",
    "t": "20秒"
  },
  {
    "id": "D_S3_013",
    "type": "口算",
    "chapter": 3,
    "kp": "简便计算综合",
    "diff": "基础",
    "q": "计算：360÷4÷9=？(简便计算)",
    "ans": "10",
    "exp": "360÷(4×9)=360÷36=10。",
    "t": "20秒"
  },
  {
    "id": "D_S3_014",
    "type": "口算",
    "chapter": 3,
    "kp": "简便计算综合",
    "diff": "中等",
    "q": "计算：99×56+56=？(简便计算)",
    "ans": "5600",
    "exp": "56×(99+1)=56×100=5600。",
    "t": "25秒"
  },
  {
    "id": "D_S3_015",
    "type": "选择题",
    "chapter": 3,
    "kp": "乘法运算律",
    "diff": "中等",
    "q": "25×(40×8)与下面哪个算式结果相同？",
    "opts": [
      "A.25×40+25×8",
      "B.25×40×8",
      "C.25×40×25×8",
      "D.25×40+8"
    ],
    "ans": "B",
    "exp": "乘法结合律：25×(40×8)=(25×40)×8。",
    "t": "20秒"
  },
  {
    "id": "D_S3_016",
    "type": "口算",
    "chapter": 3,
    "kp": "简便计算综合",
    "diff": "中等",
    "q": "计算：156-78-22=？",
    "ans": "56",
    "exp": "156-(78+22)=156-100=56。",
    "t": "20秒"
  },
  {
    "id": "D_S3_017",
    "type": "应用题",
    "chapter": 3,
    "kp": "简便计算综合",
    "diff": "中等",
    "q": "学校买来4箱打印纸，每箱25包，每包80张。一共买了多少张打印纸？",
    "ans": "8000张",
    "exp": "4×25×80=100×80=8000。",
    "t": "25秒"
  },
  {
    "id": "D_S3_018",
    "type": "口算",
    "chapter": 3,
    "kp": "简便计算综合",
    "diff": "中等",
    "q": "计算：125×25×32=？(简便计算)",
    "ans": "100000",
    "exp": "125×25×(4×8)=(125×8)×(25×4)=1000×100=100000。",
    "t": "30秒"
  },
  {
    "id": "D_S3_019",
    "type": "口算",
    "chapter": 3,
    "kp": "简便计算综合",
    "diff": "基础",
    "q": "计算：85×101=？",
    "ans": "8585",
    "exp": "85×(100+1)=8500+85=8585。",
    "t": "20秒"
  },
  {
    "id": "D_S3_020",
    "type": "填空题",
    "chapter": 3,
    "kp": "加法运算律",
    "diff": "基础",
    "q": "下面的算式运用了什么运算律？\n(54+27)+73=54+(27+73) 用了____律",
    "ans": "加法结合",
    "exp": "三个数相加，改变结合顺序。",
    "t": "15秒"
  },
  {
    "id": "D_S3_021",
    "type": "填空题",
    "chapter": 3,
    "kp": "简便计算综合",
    "diff": "基础",
    "q": "下面的算式运用了什么运算律？\n56×19+56×81=56×(19+81) 用了____律",
    "ans": "乘法分配",
    "exp": "乘法分配律的逆用。",
    "t": "15秒"
  },
  {
    "id": "D_S3_022",
    "type": "口算",
    "chapter": 3,
    "kp": "简便计算综合",
    "diff": "基础",
    "q": "250×13×4=？",
    "ans": "13000",
    "exp": "250×4×13=1000×13=13000。",
    "t": "20秒"
  },
  {
    "id": "D_S3_023",
    "type": "口算",
    "chapter": 3,
    "kp": "简便计算综合",
    "diff": "中等",
    "q": "43×67+67×57=？",
    "ans": "6700",
    "exp": "67×(43+57)=67×100=6700。",
    "t": "20秒"
  },
  {
    "id": "D_S3_024",
    "type": "口算",
    "chapter": 3,
    "kp": "简便计算综合",
    "diff": "中等",
    "q": "360÷12÷5=？",
    "ans": "6",
    "exp": "360÷(12×5)=360÷60=6。",
    "t": "20秒"
  },
  {
    "id": "D_S3_025",
    "type": "选择题",
    "chapter": 3,
    "kp": "简便计算综合",
    "diff": "中等",
    "q": "下面算式运用了乘法结合律的是？",
    "opts": [
      "A.25×8=8×25",
      "B.(5×4)×25=5×(4×25)",
      "C.36×101=36×100+36",
      "D.16×4+16×6=16×(4+6)"
    ],
    "ans": "B",
    "exp": "A交换律，B结合律，C/D分配律。",
    "t": "20秒"
  },
  {
    "id": "D_S3_026",
    "type": "口算",
    "chapter": 3,
    "kp": "简便计算综合",
    "diff": "基础",
    "q": "125×32×25=？(简便计算)",
    "ans": "100000",
    "exp": "(125×8)×(25×4)=1000×100=100000。",
    "t": "25秒"
  },
  {
    "id": "D_S3_027",
    "type": "口算",
    "chapter": 3,
    "kp": "简便计算综合",
    "diff": "中等",
    "q": "48×125=？(简便计算)",
    "ans": "6000",
    "exp": "6×(8×125)=6×1000=6000。",
    "t": "20秒"
  },
  {
    "id": "D_S3_028",
    "type": "口算",
    "chapter": 3,
    "kp": "简便计算综合",
    "diff": "基础",
    "q": "135+39+65+261=？",
    "ans": "500",
    "exp": "(135+65)+(39+261)=200+300=500。",
    "t": "20秒"
  },
  {
    "id": "D_S3_029",
    "type": "口算",
    "chapter": 3,
    "kp": "简便计算综合",
    "diff": "中等",
    "q": "58×101-58=？",
    "ans": "5800",
    "exp": "58×(101-1)=58×100=5800。",
    "t": "20秒"
  },
  {
    "id": "D_S3_030",
    "type": "填空题",
    "chapter": 3,
    "kp": "简便计算综合",
    "diff": "中等",
    "q": "450-36-64=450-(____+____)=____",
    "ans": "36；64；350",
    "exp": "连减等于减去和。",
    "t": "15秒"
  },
  {
    "id": "D_S3_031",
    "type": "口算",
    "chapter": 3,
    "kp": "简便计算综合",
    "diff": "中等",
    "q": "630÷35=？(简便计算)",
    "ans": "18",
    "exp": "630÷(7×5)=630÷7÷5=90÷5=18。",
    "t": "25秒"
  },
  {
    "id": "D_S3_032",
    "type": "应用题",
    "chapter": 3,
    "kp": "简便计算综合",
    "diff": "提高",
    "q": "一个书架有4层，每层放了25本书。每个书有56页。4层书架的书一共有多少页？(用两种方法解答)",
    "ans": "5600页",
    "exp": "方法一：4×25×56=100×56=5600。方法二：先算一层再×4。",
    "t": "30秒"
  },
  {
    "id": "D_S3_033",
    "type": "口算",
    "chapter": 3,
    "kp": "简便计算综合",
    "diff": "中等",
    "q": "35×104=？(简便计算)",
    "ans": "3640",
    "exp": "35×(100+4)=35×100+35×4=3500+140=3640。",
    "t": "20秒"
  },
  {
    "id": "D_S3_034",
    "type": "口算",
    "chapter": 3,
    "kp": "简便计算综合",
    "diff": "基础",
    "q": "25+98+75=？",
    "ans": "198",
    "exp": "25+75+98=100+98=198。",
    "t": "15秒"
  },
  {
    "id": "D_S3_035",
    "type": "应用题",
    "chapter": 3,
    "kp": "简便计算综合",
    "diff": "提高",
    "q": "李叔叔骑车旅行，前3天骑了88+104+96千米，后4天骑了110+92+113+85千米。李叔叔7天一共骑了多少千米？用简便计算。",
    "ans": "688千米",
    "exp": "(88+92)+(104+96)+(110)+(113+85)=180+200+110+198=688。",
    "t": "40秒"
  },
  {
    "id": "D_S4_001",
    "type": "填空题",
    "chapter": 4,
    "kp": "小数的意义",
    "diff": "基础",
    "q": "把单位1平均分成10份，其中的1份是____，用小数表示是____。",
    "ans": "十分之一；0.1",
    "exp": "1/10=0.1。",
    "t": "15秒"
  },
  {
    "id": "D_S4_002",
    "type": "填空题",
    "chapter": 4,
    "kp": "小数的意义",
    "diff": "基础",
    "q": "0.1里面有____个0.01，0.01里面有____个0.001。",
    "ans": "10；10",
    "exp": "相邻计数单位进率10。",
    "t": "15秒"
  },
  {
    "id": "D_S4_003",
    "type": "选择题",
    "chapter": 4,
    "kp": "小数的意义",
    "diff": "基础",
    "q": "0.5的计数单位是？",
    "opts": [
      "A.1",
      "B.0.1",
      "C.0.01",
      "D.0.001"
    ],
    "ans": "B",
    "exp": "0.5=5个0.1，计数单位0.1。",
    "t": "15秒"
  },
  {
    "id": "D_S4_004",
    "type": "填空题",
    "chapter": 4,
    "kp": "小数的意义",
    "diff": "基础",
    "q": "3.07的计数单位是____，它有____个这样的计数单位。",
    "ans": "0.01；307",
    "exp": "3.07=307个0.01。",
    "t": "20秒"
  },
  {
    "id": "D_S4_005",
    "type": "填空题",
    "chapter": 4,
    "kp": "小数的意义",
    "diff": "基础",
    "q": "小数点右边第二位是____位，计数单位是____。",
    "ans": "百分；0.01",
    "exp": "十分位(0.1)→百分位(0.01)→千分位(0.001)。",
    "t": "15秒"
  },
  {
    "id": "D_S4_006",
    "type": "口算",
    "chapter": 4,
    "kp": "小数的读写",
    "diff": "基础",
    "q": "读出：3.506",
    "ans": "三点五零六",
    "exp": "整数部分按整数读，小数部分顺次读数字。",
    "t": "15秒"
  },
  {
    "id": "D_S4_007",
    "type": "填空题",
    "chapter": 4,
    "kp": "小数的读写",
    "diff": "基础",
    "q": "三点零七五写作：____",
    "ans": "3.075",
    "exp": "整数部分3，小数点后依次写075。",
    "t": "15秒"
  },
  {
    "id": "D_S4_008",
    "type": "选择题",
    "chapter": 4,
    "kp": "小数的性质",
    "diff": "基础",
    "q": "下面各数中，哪个去掉0后大小不变？",
    "opts": [
      "A.4.05",
      "B.4.50",
      "C.450",
      "D.40.5"
    ],
    "ans": "B",
    "exp": "小数的末尾去掉0大小不变，4.50=4.5。",
    "t": "15秒"
  },
  {
    "id": "D_S4_009",
    "type": "口算",
    "chapter": 4,
    "kp": "小数的性质",
    "diff": "基础",
    "q": "化简小数：0.200=____，3.0600=____",
    "ans": "0.2；3.06",
    "exp": "去掉小数末尾的0。",
    "t": "15秒"
  },
  {
    "id": "D_S4_010",
    "type": "口算",
    "chapter": 4,
    "kp": "小数大小比较",
    "diff": "基础",
    "q": "比较大小：3.14____3.14",
    "ans": "=",
    "exp": "相等。",
    "t": "10秒"
  },
  {
    "id": "D_S4_011",
    "type": "口算",
    "chapter": 4,
    "kp": "小数大小比较",
    "diff": "基础",
    "q": "比较大小：0.8____0.79",
    "ans": ">",
    "exp": "十分位8>7。",
    "t": "10秒"
  },
  {
    "id": "D_S4_012",
    "type": "选择题",
    "chapter": 4,
    "kp": "小数大小比较",
    "diff": "基础",
    "q": "下面各数中最大的是？",
    "opts": [
      "A.4.05",
      "B.4.5",
      "C.4.055",
      "D.4.55"
    ],
    "ans": "D",
    "exp": "4.55>4.5>4.055>4.05。",
    "t": "20秒"
  },
  {
    "id": "D_S4_013",
    "type": "应用题",
    "chapter": 4,
    "kp": "小数大小比较",
    "diff": "中等",
    "q": "四位同学跳远成绩：小明2.84m，小刚2.86m，小芳2.79m，小红2.80m。请从高到低排序。",
    "ans": "小刚2.86m＞小明2.84m＞小红2.80m＞小芳2.79m",
    "exp": "小数的比较，从整数到小数逐位比。",
    "t": "25秒"
  },
  {
    "id": "D_S4_014",
    "type": "口算",
    "chapter": 4,
    "kp": "小数点移动",
    "diff": "基础",
    "q": "把0.07的小数点向右移动一位是____，相当于扩大到原来的____倍。",
    "ans": "0.7；10",
    "exp": "右移1位，×10。",
    "t": "15秒"
  },
  {
    "id": "D_S4_015",
    "type": "口算",
    "chapter": 4,
    "kp": "小数点移动",
    "diff": "基础",
    "q": "把3.14的小数点向左移动两位是____，相当于缩小到原来的____。",
    "ans": "0.0314；1/100",
    "exp": "左移2位，÷100。",
    "t": "15秒"
  },
  {
    "id": "D_S4_016",
    "type": "口算",
    "chapter": 4,
    "kp": "小数点移动",
    "diff": "基础",
    "q": "把2.5扩大到100倍是____。",
    "ans": "250",
    "exp": "小数点向右移动两位。",
    "t": "15秒"
  },
  {
    "id": "D_S4_017",
    "type": "口算",
    "chapter": 4,
    "kp": "小数点移动",
    "diff": "基础",
    "q": "把450缩小到1/1000是____。",
    "ans": "0.45",
    "exp": "小数点向左移动三位：450→4.50→0.45。",
    "t": "15秒"
  },
  {
    "id": "D_S4_018",
    "type": "填空题",
    "chapter": 4,
    "kp": "小数与单位换算",
    "diff": "中等",
    "q": "3.05米=____米____厘米",
    "ans": "3；5",
    "exp": "3.05m=3m+0.05m=3m+5cm。",
    "t": "20秒"
  },
  {
    "id": "D_S4_019",
    "type": "口算",
    "chapter": 4,
    "kp": "小数与单位换算",
    "diff": "中等",
    "q": "2.6千克=____克",
    "ans": "2600",
    "exp": "1kg=1000g, 2.6×1000=2600。",
    "t": "15秒"
  },
  {
    "id": "D_S4_020",
    "type": "口算",
    "chapter": 4,
    "kp": "小数与单位换算",
    "diff": "中等",
    "q": "800平方米=____公顷",
    "ans": "0.08",
    "exp": "1公顷=10000平方米, 800÷10000=0.08。",
    "t": "15秒"
  },
  {
    "id": "D_S4_021",
    "type": "口算",
    "chapter": 4,
    "kp": "小数与单位换算",
    "diff": "中等",
    "q": "5吨60千克=____吨",
    "ans": "5.06",
    "exp": "60kg=0.06t, 5+0.06=5.06。",
    "t": "20秒"
  },
  {
    "id": "D_S4_022",
    "type": "口算",
    "chapter": 4,
    "kp": "小数与单位换算",
    "diff": "中等",
    "q": "0.48平方米=____平方分米",
    "ans": "48",
    "exp": "1平方米=100平方分米, 0.48×100=48。",
    "t": "15秒"
  },
  {
    "id": "D_S4_023",
    "type": "填空题",
    "chapter": 4,
    "kp": "小数的近似数",
    "diff": "中等",
    "q": "0.984≈____（保留整数），≈____（保留一位小数），≈____（保留两位小数）",
    "ans": "1；1.0；0.98",
    "exp": "四舍五入：0.984十分位9→1，百分位8→0.98。",
    "t": "25秒"
  },
  {
    "id": "D_S4_024",
    "type": "填空题",
    "chapter": 4,
    "kp": "小数的近似数",
    "diff": "中等",
    "q": "将345600000改写成用'亿'作单位的数并保留两位小数：____",
    "ans": "3.46亿",
    "exp": "345600000=3.456亿≈3.46亿。",
    "t": "25秒"
  },
  {
    "id": "D_S4_025",
    "type": "选择题",
    "chapter": 4,
    "kp": "小数的近似数",
    "diff": "中等",
    "q": "一个三位小数精确到百分位后约是3.50，这个小数最大是（ ）。",
    "opts": [
      "A.3.499",
      "B.3.504",
      "C.3.509",
      "D.3.495"
    ],
    "ans": "B",
    "exp": "四舍得3.50最大是3.504（千分位4）。",
    "t": "30秒"
  },
  {
    "id": "D_S4_026",
    "type": "口算",
    "chapter": 4,
    "kp": "小数的意义",
    "diff": "基础",
    "q": "0.8里面有____个0.1，0.035里面有____个0.001。",
    "ans": "8；35",
    "exp": "计数单位换算。",
    "t": "15秒"
  },
  {
    "id": "D_S4_027",
    "type": "选择题",
    "chapter": 4,
    "kp": "小数的性质",
    "diff": "基础",
    "q": "与3.050相等的数是？",
    "opts": [
      "A.3.05",
      "B.3.500",
      "C.3.005",
      "D.3.5"
    ],
    "ans": "A",
    "exp": "去掉小数末尾的0，3.050=3.05。",
    "t": "15秒"
  },
  {
    "id": "D_S4_028",
    "type": "口算",
    "chapter": 4,
    "kp": "小数点移动",
    "diff": "基础",
    "q": "一个数的小数点向右移动两位后是235，这个数原来是____。",
    "ans": "2.35",
    "exp": "扩大100倍是235，原数为235÷100=2.35。",
    "t": "15秒"
  },
  {
    "id": "D_S4_029",
    "type": "口算",
    "chapter": 4,
    "kp": "小数与单位换算",
    "diff": "中等",
    "q": "3.6千米=____米，2500米=____千米",
    "ans": "3600；2.5",
    "exp": "×1000和÷1000。",
    "t": "15秒"
  },
  {
    "id": "D_S4_030",
    "type": "应用题",
    "chapter": 4,
    "kp": "小数的近似数",
    "diff": "提高",
    "q": "一个两位小数用四舍五入法精确到十分位后是8.0，这个两位小数最大是多少？最小是多少？",
    "ans": "最大8.04；最小7.95",
    "exp": "最大：8.04的四舍≈8.0。最小：7.95的五入≈8.0。",
    "t": "30秒"
  },
  {
    "id": "D_S4_031",
    "type": "填空题",
    "chapter": 4,
    "kp": "小数的意义",
    "diff": "基础",
    "q": "0.7的计数单位是____，它有____个这样的单位；0.70的计数单位是____，它有____个这样的单位。",
    "ans": "0.1；7；0.01；70",
    "exp": "计数单位不同但大小相等。",
    "t": "15秒"
  },
  {
    "id": "D_S4_032",
    "type": "口算",
    "chapter": 4,
    "kp": "小数点移动",
    "diff": "基础",
    "q": "把3.6×100=____，÷10=____，÷1000=____",
    "ans": "360；36；0.036",
    "exp": "小数点移动。",
    "t": "15秒"
  },
  {
    "id": "D_S4_033",
    "type": "口算",
    "chapter": 4,
    "kp": "小数与单位换算",
    "diff": "中等",
    "q": "780克=____千克",
    "ans": "0.78",
    "exp": "1kg=1000g, 780÷1000=0.78。",
    "t": "15秒"
  },
  {
    "id": "D_S4_034",
    "type": "选择题",
    "chapter": 4,
    "kp": "小数大小比较",
    "diff": "基础",
    "q": "0.6,0.60,0.600这三个数？",
    "opts": [
      "A.大小不等",
      "B.大小相等",
      "C.0.6最小",
      "D.0.600最大"
    ],
    "ans": "B",
    "exp": "小数的性质，后面加0大小不变。",
    "t": "15秒"
  },
  {
    "id": "D_S4_035",
    "type": "填空题",
    "chapter": 4,
    "kp": "小数与单位换算",
    "diff": "中等",
    "q": "3.5公顷=____平方米，0.8平方千米=____公顷",
    "ans": "35000；80",
    "exp": "公顷×10000→平方米，平方千米×100→公顷。",
    "t": "15秒"
  },
  {
    "id": "D_S4_036",
    "type": "口算",
    "chapter": 4,
    "kp": "小数与单位换算",
    "diff": "中等",
    "q": "1.05吨=____吨____千克",
    "ans": "1；50",
    "exp": "0.05t=50kg, 1又50/1000吨=0.05吨? 1吨=1000kg, 0.05t=50kg。所以1.05t=1t50kg。",
    "t": "20秒"
  },
  {
    "id": "D_S4_037",
    "type": "口算",
    "chapter": 4,
    "kp": "小数大小比较",
    "diff": "基础",
    "q": "按从小到大的排序：0.35, 0.305, 0.35(0.35本身), 0.3",
    "ans": "0.3 < 0.305 < 0.35",
    "exp": "0.3=0.300, 0.305, 0.35=0.350。",
    "t": "20秒"
  },
  {
    "id": "D_S4_038",
    "type": "口算",
    "chapter": 4,
    "kp": "小数的性质",
    "diff": "基础",
    "q": "不改变大小，把3.1改写成三位小数是____。",
    "ans": "3.100",
    "exp": "小数末尾添0。",
    "t": "15秒"
  },
  {
    "id": "D_S4_039",
    "type": "选择题",
    "chapter": 4,
    "kp": "小数的近似数",
    "diff": "中等",
    "q": "一个三位小数四舍五入到百分位约是2.85，这个三位小数最大是？",
    "opts": [
      "A.2.849",
      "B.2.850",
      "C.2.854",
      "D.2.855"
    ],
    "ans": "C",
    "exp": "四舍得2.85最大为2.854。",
    "t": "25秒"
  },
  {
    "id": "D_S4_040",
    "type": "应用题",
    "chapter": 4,
    "kp": "小数与单位换算",
    "diff": "提高",
    "q": "一根绳子长10米，第一次剪去3.65米，第二次剪去2.35米，还剩多少米？（用简便方法）",
    "ans": "4米",
    "exp": "10-(3.65+2.35)=10-6=4。",
    "t": "20秒"
  },
  {
    "id": "D_S5_001",
    "type": "填空题",
    "chapter": 5,
    "kp": "三角形的特性",
    "diff": "基础",
    "q": "三角形有____条边，____个角，____个顶点。",
    "ans": "3；3；3",
    "exp": "三角形的特征。",
    "t": "10秒"
  },
  {
    "id": "D_S5_002",
    "type": "填空题",
    "chapter": 5,
    "kp": "三角形的特性",
    "diff": "基础",
    "q": "三角形具有____性，而平行四边形具有____性。",
    "ans": "稳定；不稳定(易变形)",
    "exp": "三角形的稳定性和平行四边形的不稳定性。",
    "t": "15秒"
  },
  {
    "id": "D_S5_003",
    "type": "选择题",
    "chapter": 5,
    "kp": "三角形的特性",
    "diff": "基础",
    "q": "下面哪组的三根小棒能围成三角形？",
    "opts": [
      "A.3cm,4cm,8cm",
      "B.5cm,5cm,10cm",
      "C.5cm,6cm,10cm",
      "D.2cm,3cm,6cm"
    ],
    "ans": "C",
    "exp": "三角形两边之和大于第三边。A:3+4<8, B:5+5=10(不大于), C:5+6=11>10, D:2+3<6。",
    "t": "25秒"
  },
  {
    "id": "D_S5_004",
    "type": "口算",
    "chapter": 5,
    "kp": "三角形的特性",
    "diff": "基础",
    "q": "从三角形的一个顶点到它对边作一条垂线，____和____之间的线段叫做三角形的高。",
    "ans": "顶点；垂足",
    "exp": "三角形高的定义。",
    "t": "15秒"
  },
  {
    "id": "D_S5_005",
    "type": "填空题",
    "chapter": 5,
    "kp": "三角形的分类",
    "diff": "基础",
    "q": "三角形按角分可分为：____三角形、____三角形和____三角形。",
    "ans": "锐角；直角；钝角",
    "exp": "按角分类。",
    "t": "15秒"
  },
  {
    "id": "D_S5_006",
    "type": "选择题",
    "chapter": 5,
    "kp": "三角形的分类",
    "diff": "基础",
    "q": "一个三角形中有一个角是120°，这个三角形是？",
    "opts": [
      "A.锐角三角形",
      "B.直角三角形",
      "C.钝角三角形",
      "D.等边三角形"
    ],
    "ans": "C",
    "exp": "120°>90°，是钝角三角形。",
    "t": "15秒"
  },
  {
    "id": "D_S5_007",
    "type": "填空题",
    "chapter": 5,
    "kp": "三角形的分类",
    "diff": "基础",
    "q": "____条边相等的三角形叫做等腰三角形，____条边相等的三角形叫做等边三角形。",
    "ans": "两；三",
    "exp": "等腰和等边的定义。",
    "t": "15秒"
  },
  {
    "id": "D_S5_008",
    "type": "填空题",
    "chapter": 5,
    "kp": "三角形的分类",
    "diff": "基础",
    "q": "等边三角形的每个角都是____°，它是特殊的____三角形。",
    "ans": "60；等腰",
    "exp": "等边三角形三边相等，三角都60°。",
    "t": "15秒"
  },
  {
    "id": "D_S5_009",
    "type": "口算",
    "chapter": 5,
    "kp": "三角形内角和",
    "diff": "基础",
    "q": "三角形的内角和等于____°。",
    "ans": "180",
    "exp": "三角形内角和定理。",
    "t": "10秒"
  },
  {
    "id": "D_S5_010",
    "type": "口算",
    "chapter": 5,
    "kp": "三角形内角和",
    "diff": "基础",
    "q": "在直角三角形中，两个锐角的和是____°。",
    "ans": "90",
    "exp": "180-90=90。",
    "t": "10秒"
  },
  {
    "id": "D_S5_011",
    "type": "口算",
    "chapter": 5,
    "kp": "三角形内角和",
    "diff": "基础",
    "q": "一个三角形中∠1=45°，∠2=65°，∠3=____°",
    "ans": "70",
    "exp": "180-45-65=70。",
    "t": "15秒"
  },
  {
    "id": "D_S5_012",
    "type": "口算",
    "chapter": 5,
    "kp": "三角形内角和",
    "diff": "基础",
    "q": "一个等腰三角形的顶角是80°，它的一个底角是____°。",
    "ans": "50",
    "exp": "底角=(180-80)÷2=50°。",
    "t": "20秒"
  },
  {
    "id": "D_S5_013",
    "type": "选择题",
    "chapter": 5,
    "kp": "三角形的特性",
    "diff": "基础",
    "q": "学校的伸缩门应用了（ ）的原理。",
    "opts": [
      "A.三角形的稳定性",
      "B.平行四边形的不稳定性",
      "C.两点确定一条直线",
      "D.轴对称"
    ],
    "ans": "B",
    "exp": "伸缩门利用平行四边形容易变形的特性。",
    "t": "15秒"
  },
  {
    "id": "D_S5_014",
    "type": "口算",
    "chapter": 5,
    "kp": "三角形内角和",
    "diff": "中等",
    "q": "一个等腰三角形的一个底角是40°，它的顶角是____°。",
    "ans": "100",
    "exp": "180-40×2=100°。",
    "t": "15秒"
  },
  {
    "id": "D_S5_015",
    "type": "填空题",
    "chapter": 5,
    "kp": "三角形的特性",
    "diff": "中等",
    "q": "三角形任意两边之和____第三边，任意两边之差____第三边。",
    "ans": "大于；小于",
    "exp": "三角形三边关系。",
    "t": "15秒"
  },
  {
    "id": "D_S5_016",
    "type": "应用题",
    "chapter": 5,
    "kp": "三角形的特性",
    "diff": "中等",
    "q": "用一根24厘米长的铁丝围成一个三角形，如果最长的一条边最长可以是多少厘米？（取整厘米）",
    "ans": "11厘米",
    "exp": "最长边<周长的一半=12，最大整数为11cm（其他两边和13>11）。",
    "t": "30秒"
  },
  {
    "id": "D_S5_017",
    "type": "口算",
    "chapter": 5,
    "kp": "三角形的分类",
    "diff": "基础",
    "q": "等腰三角形两____相等，等边三角形三____都相等。",
    "ans": "腰；边",
    "exp": "等腰两腰相等，等边三边相等。",
    "t": "10秒"
  },
  {
    "id": "D_S5_018",
    "type": "选择题",
    "chapter": 5,
    "kp": "三角形的分类",
    "diff": "基础",
    "q": "等腰直角三角形的顶角（直角三角形的直角作为顶角时）两个底角分别是多少度？",
    "opts": [
      "A.60°和60°",
      "B.45°和45°",
      "C.30°和60°",
      "D.50°和40°"
    ],
    "ans": "B",
    "exp": "直角三角形中非直角的两角互余，等腰则两底角相等：90÷2=45°。",
    "t": "20秒"
  },
  {
    "id": "D_S5_019",
    "type": "填空题",
    "chapter": 5,
    "kp": "三角形的分类",
    "diff": "基础",
    "q": "在一个三角形中，最大的角是89°，这个三角形是____三角形。",
    "ans": "锐角",
    "exp": "最大角89°<90°，所以三个角都是锐角。",
    "t": "15秒"
  },
  {
    "id": "D_S5_020",
    "type": "口算",
    "chapter": 5,
    "kp": "三角形内角和",
    "diff": "中等",
    "q": "四边形内角和=____°（可以分成____个三角形来求）",
    "ans": "360；2",
    "exp": "四边形分成2个三角形：2×180=360°。",
    "t": "20秒"
  },
  {
    "id": "D_S5_021",
    "type": "应用题",
    "chapter": 5,
    "kp": "三角形内角和",
    "diff": "提高",
    "q": "一个三角形中，∠1是∠2的2倍，∠3比∠1大30°，求三个角各是多少度？",
    "ans": "∠1=60°, ∠2=30°, ∠3=90°",
    "exp": "设∠2=x, ∠1=2x, ∠3=2x+30。x+2x+2x+30=180, 5x=150, x=30。",
    "t": "50秒"
  },
  {
    "id": "D_S5_022",
    "type": "填空题",
    "chapter": 5,
    "kp": "三角形的特性",
    "diff": "基础",
    "q": "一个三角形有____条高。",
    "ans": "3",
    "exp": "三条边各对应一条高。",
    "t": "10秒"
  },
  {
    "id": "D_S5_023",
    "type": "选择题",
    "chapter": 5,
    "kp": "三角形的特性",
    "diff": "基础",
    "q": "下面长度能组成三角形的是？",
    "opts": [
      "A.3cm,4cm,7cm",
      "B.4cm,5cm,10cm",
      "C.6cm,7cm,8cm",
      "D.1cm,2cm,3cm"
    ],
    "ans": "C",
    "exp": "6+7>8且差<8，其他都不满足两边之和大于第三边。",
    "t": "20秒"
  },
  {
    "id": "D_S5_024",
    "type": "填空题",
    "chapter": 5,
    "kp": "三角形的分类",
    "diff": "基础",
    "q": "等腰三角形的一个底角是70°，它的顶角是____°，它按角分是____三角形。",
    "ans": "40；锐角",
    "exp": "顶角=180-70×2=40°，三个都是锐角。",
    "t": "20秒"
  },
  {
    "id": "D_S5_025",
    "type": "口算",
    "chapter": 5,
    "kp": "三角形内角和",
    "diff": "中等",
    "q": "有一个三角形，∠1=90°，∠2=30°，∠3=____°，它是____三角形。",
    "ans": "60；直角",
    "exp": "180-90-30=60°，有直角，是直角三角形。",
    "t": "15秒"
  },
  {
    "id": "D_S6_001",
    "type": "口算",
    "chapter": 6,
    "kp": "小数加减法",
    "diff": "基础",
    "q": "0.6+0.3=____",
    "ans": "0.9",
    "exp": "十分位上6+3=9。",
    "t": "10秒"
  },
  {
    "id": "D_S6_002",
    "type": "口算",
    "chapter": 6,
    "kp": "小数加减法",
    "diff": "基础",
    "q": "2.5-1.3=____",
    "ans": "1.2",
    "exp": "2.5-1.3=1.2。",
    "t": "10秒"
  },
  {
    "id": "D_S6_003",
    "type": "口算",
    "chapter": 6,
    "kp": "小数加减法",
    "diff": "基础",
    "q": "0.28+0.35=____",
    "ans": "0.63",
    "exp": "0.28+0.35=0.63。",
    "t": "10秒"
  },
  {
    "id": "D_S6_004",
    "type": "口算",
    "chapter": 6,
    "kp": "小数加减法",
    "diff": "基础",
    "q": "3.7+6.3=____",
    "ans": "10",
    "exp": "3.7+6.3=10。",
    "t": "10秒"
  },
  {
    "id": "D_S6_005",
    "type": "口算",
    "chapter": 6,
    "kp": "小数加减法",
    "diff": "基础",
    "q": "4-0.9=____",
    "ans": "3.1",
    "exp": "4.0-0.9=3.1。",
    "t": "10秒"
  },
  {
    "id": "D_S6_006",
    "type": "口算",
    "chapter": 6,
    "kp": "小数加减法",
    "diff": "基础",
    "q": "5.3-3.8=____",
    "ans": "1.5",
    "exp": "5.3-3.8=1.5。",
    "t": "10秒"
  },
  {
    "id": "D_S6_007",
    "type": "填空题",
    "chapter": 6,
    "kp": "小数加减法",
    "diff": "基础",
    "q": "计算小数加减法时，先把____对齐，也就是把相同数位对齐。",
    "ans": "小数点",
    "exp": "小数点对齐即相同数位对齐。",
    "t": "10秒"
  },
  {
    "id": "D_S6_008",
    "type": "口算",
    "chapter": 6,
    "kp": "小数加减法",
    "diff": "基础",
    "q": "7.5+2.5=____，12.3-2.3=____",
    "ans": "10；10",
    "exp": "简便计算。",
    "t": "10秒"
  },
  {
    "id": "D_S6_009",
    "type": "口算",
    "chapter": 6,
    "kp": "小数加减法",
    "diff": "中等",
    "q": "9.8+0.2-9.8+0.2=____",
    "ans": "0.4",
    "exp": "(9.8-9.8)+(0.2+0.2)=0+0.4=0.4。",
    "t": "20秒"
  },
  {
    "id": "D_S6_010",
    "type": "口算",
    "chapter": 6,
    "kp": "小数加减混合",
    "diff": "中等",
    "q": "3.65+2.35-3.65+2.35=____",
    "ans": "4.7",
    "exp": "(3.65-3.65)+(2.35+2.35)=0+4.7=4.7。",
    "t": "20秒"
  },
  {
    "id": "D_S6_011",
    "type": "填空题",
    "chapter": 6,
    "kp": "小数加减法",
    "diff": "基础",
    "q": "计算小数减法时，当被减数的小数位数不够时，可以在末尾____再减。",
    "ans": "补0",
    "exp": "如3.1-0.85→3.10-0.85。",
    "t": "15秒"
  },
  {
    "id": "D_S6_012",
    "type": "口算",
    "chapter": 6,
    "kp": "小数加减法",
    "diff": "基础",
    "q": "1.25+3.75=____",
    "ans": "5",
    "exp": "1.25+3.75=5。",
    "t": "10秒"
  },
  {
    "id": "D_S6_013",
    "type": "口算",
    "chapter": 6,
    "kp": "小数加减混合",
    "diff": "基础",
    "q": "10-3.6-5.4=____（简便计算）",
    "ans": "1",
    "exp": "10-(3.6+5.4)=10-9=1。",
    "t": "20秒"
  },
  {
    "id": "D_S6_014",
    "type": "口算",
    "chapter": 6,
    "kp": "小数加减混合",
    "diff": "中等",
    "q": "16.7+2.9+3.3=____（简便计算）",
    "ans": "22.9",
    "exp": "16.7+3.3+2.9=20+2.9=22.9。",
    "t": "15秒"
  },
  {
    "id": "D_S6_015",
    "type": "选择题",
    "chapter": 6,
    "kp": "小数加减法",
    "diff": "基础",
    "q": "下面哪个算式的结果是整数？",
    "opts": [
      "A.3.6+0.4",
      "B.2.5+1.5",
      "C.6.3-0.3",
      "D.以上都对"
    ],
    "ans": "D",
    "exp": "A=4, B=4, C=6。",
    "t": "15秒"
  },
  {
    "id": "D_S6_016",
    "type": "口算",
    "chapter": 6,
    "kp": "小数加减法",
    "diff": "基础",
    "q": "0.06+0.94=____",
    "ans": "1",
    "exp": "0.06+0.94=1。",
    "t": "10秒"
  },
  {
    "id": "D_S6_017",
    "type": "口算",
    "chapter": 6,
    "kp": "小数加减法",
    "diff": "基础",
    "q": "8.5-0.5=____",
    "ans": "8",
    "exp": "8.5-0.5=8。",
    "t": "10秒"
  },
  {
    "id": "D_S6_018",
    "type": "应用题",
    "chapter": 6,
    "kp": "小数加减混合",
    "diff": "中等",
    "q": "一根铁丝长4.8米，第一次剪去1.25米，第二次剪去0.75米，还剩多少米？（用简便方法）",
    "ans": "2.8米",
    "exp": "4.8-(1.25+0.75)=4.8-2=2.8。",
    "t": "20秒"
  },
  {
    "id": "D_S6_019",
    "type": "口算",
    "chapter": 6,
    "kp": "小数加减混合",
    "diff": "中等",
    "q": "0.25+0.75+1.2+2.8=____",
    "ans": "5",
    "exp": "(0.25+0.75)+(1.2+2.8)=1+4=5。",
    "t": "15秒"
  },
  {
    "id": "D_S6_020",
    "type": "口算",
    "chapter": 6,
    "kp": "小数加减法",
    "diff": "基础",
    "q": "12-7.4=____",
    "ans": "4.6",
    "exp": "12.0-7.4=4.6。",
    "t": "15秒"
  },
  {
    "id": "D_S6_021",
    "type": "口算",
    "chapter": 6,
    "kp": "小数加减法",
    "diff": "基础",
    "q": "9.8+0.6=____",
    "ans": "10.4",
    "exp": "9.8+0.6=10.4。",
    "t": "10秒"
  },
  {
    "id": "D_S6_022",
    "type": "口算",
    "chapter": 6,
    "kp": "小数加减法",
    "diff": "基础",
    "q": "7.2-1.8=____",
    "ans": "5.4",
    "exp": "7.2-1.8=5.4。",
    "t": "10秒"
  },
  {
    "id": "D_S6_023",
    "type": "口算",
    "chapter": 6,
    "kp": "小数加减混合",
    "diff": "中等",
    "q": "3.8+4.5+6.2+5.5=____（简便计算）",
    "ans": "20",
    "exp": "(3.8+6.2)+(4.5+5.5)=10+10=20。",
    "t": "15秒"
  },
  {
    "id": "D_S6_024",
    "type": "应用题",
    "chapter": 6,
    "kp": "小数加减法",
    "diff": "中等",
    "q": "妈妈买了3.5千克苹果和2.5千克梨，每千克苹果5.6元，每千克梨3.4元，一共花了多少钱？(用简便方法)",
    "ans": "28.7元",
    "exp": "3.5×5.6+2.5×3.4 或简算。更简便：(5.6+3.4)×3.5=9×3.5=31.5。等等重新算：3.5×5.6=19.6, 2.5×3.4=8.5, 总共28.1。",
    "t": "35秒"
  },
  {
    "id": "D_S6_025",
    "type": "应用题",
    "chapter": 6,
    "kp": "小数加减混合",
    "diff": "提高",
    "q": "小华买了一本书和一支笔，书比笔贵12.5元，书和笔一共花了38.5元。书和笔各多少钱？",
    "ans": "书25.5元；笔13元",
    "exp": "设笔x元，书x+12.5。x+(x+12.5)=38.5, 2x=26, x=13。书=25.5。",
    "t": "35秒"
  },
  {
    "id": "D_S7_001",
    "type": "填空题",
    "chapter": 7,
    "kp": "轴对称",
    "diff": "基础",
    "q": "一个图形沿一条直线对折后，两侧能够完全重合，这个图形叫做____图形，这条直线叫做____。",
    "ans": "轴对称；对称轴",
    "exp": "轴对称的定义。",
    "t": "15秒"
  },
  {
    "id": "D_S7_002",
    "type": "填空题",
    "chapter": 7,
    "kp": "轴对称",
    "diff": "基础",
    "q": "在轴对称图形中，对称点到对称轴的距离____。",
    "ans": "相等",
    "exp": "轴对称的性质。",
    "t": "10秒"
  },
  {
    "id": "D_S7_003",
    "type": "选择题",
    "chapter": 7,
    "kp": "轴对称",
    "diff": "基础",
    "q": "下面哪个图形是轴对称图形？",
    "opts": [
      "A.平行四边形",
      "B.等腰三角形",
      "C.直角梯形",
      "D.不等边三角形"
    ],
    "ans": "B",
    "exp": "等腰三角形是轴对称图形（底边上的高为对称轴）。",
    "t": "15秒"
  },
  {
    "id": "D_S7_004",
    "type": "填空题",
    "chapter": 7,
    "kp": "平移",
    "diff": "基础",
    "q": "平移不改变图形的____和____，只改变图形的____。",
    "ans": "大小；形状；位置",
    "exp": "平移的性质。",
    "t": "15秒"
  },
  {
    "id": "D_S7_005",
    "type": "选择题",
    "chapter": 7,
    "kp": "平移",
    "diff": "基础",
    "q": "下面现象中，（ ）是平移。",
    "opts": [
      "A.风扇转动",
      "B.抽屉拉动",
      "C.车轮转动",
      "D.钟摆摆动"
    ],
    "ans": "B",
    "exp": "抽屉拉动是平移运动。",
    "t": "15秒"
  },
  {
    "id": "D_S7_006",
    "type": "填空题",
    "chapter": 7,
    "kp": "轴对称",
    "diff": "中等",
    "q": "正方形有____条对称轴，等边三角形有____条。",
    "ans": "4；3",
    "exp": "正方形有4条，等边三角形有3条。",
    "t": "15秒"
  },
  {
    "id": "D_S7_007",
    "type": "填空题",
    "chapter": 7,
    "kp": "轴对称",
    "diff": "基础",
    "q": "长方形有____条对称轴，等腰梯形有____条。",
    "ans": "2；1",
    "exp": "长方形的对称轴是两组对边的中线。",
    "t": "15秒"
  },
  {
    "id": "D_S7_008",
    "type": "口算",
    "chapter": 7,
    "kp": "轴对称",
    "diff": "中等",
    "q": "图形先向某个方向平移几格，再向另一个方向平移几格，这样描述图形的运动。",
    "ans": "指定方向和距离",
    "exp": "平移需要说明方向和距离。",
    "t": "10秒"
  },
  {
    "id": "D_S7_009",
    "type": "填空题",
    "chapter": 7,
    "kp": "平移",
    "diff": "基础",
    "q": "一个点在方格纸上向右平移3格，它的____坐标增加3。",
    "ans": "列或横",
    "exp": "右移增加列数。",
    "t": "15秒"
  },
  {
    "id": "D_S7_010",
    "type": "选择题",
    "chapter": 7,
    "kp": "轴对称",
    "diff": "中等",
    "q": "圆有（ ）条对称轴。",
    "opts": [
      "A.1",
      "B.2",
      "C.4",
      "D.无数条"
    ],
    "ans": "D",
    "exp": "圆有无数条对称轴（任何直径）。",
    "t": "15秒"
  },
  {
    "id": "D_S7_011",
    "type": "填空题",
    "chapter": 7,
    "kp": "平移",
    "diff": "基础",
    "q": "平移后的图形和原图形的对应点所连的线段____且____。",
    "ans": "平行；相等",
    "exp": "平移对应点连线平行且相等。",
    "t": "15秒"
  },
  {
    "id": "D_S7_012",
    "type": "选择题",
    "chapter": 7,
    "kp": "轴对称",
    "diff": "中等",
    "q": "下面哪个不是轴对称图形？",
    "opts": [
      "A.正方形",
      "B.正五边形",
      "C.平行四边形",
      "D.等腰梯形"
    ],
    "ans": "C",
    "exp": "一般的平行四边形不是轴对称图形。",
    "t": "15秒"
  },
  {
    "id": "D_S7_013",
    "type": "填空题",
    "chapter": 7,
    "kp": "轴对称",
    "diff": "中等",
    "q": "正六边形有____条对称轴。",
    "ans": "6",
    "exp": "正六边形有6条对称轴。",
    "t": "15秒"
  },
  {
    "id": "D_S7_014",
    "type": "选择题",
    "chapter": 7,
    "kp": "平移",
    "diff": "中等",
    "q": "一个图形向右平移5格，再向右平移3格，相当于向（ ）平移了（ ）格。",
    "opts": [
      "A.右，2",
      "B.右，8",
      "C.左，2",
      "D.左，8"
    ],
    "ans": "B",
    "exp": "5+3=8格，向右平移8格。",
    "t": "15秒"
  },
  {
    "id": "D_S7_015",
    "type": "应用题",
    "chapter": 7,
    "kp": "轴对称与平移",
    "diff": "中等",
    "q": "你能通过（）和（）两种运动，把左边的图形变成右边的图形吗？（填空）",
    "ans": "轴对称；平移",
    "exp": "先轴对称再平移（或先平移再轴对称）。",
    "t": "20秒"
  },
  {
    "id": "D_S8_001",
    "type": "填空题",
    "chapter": 8,
    "kp": "平均数",
    "diff": "基础",
    "q": "求平均数的方法：先用____÷____=平均数。",
    "ans": "总数；份数",
    "exp": "平均数=总数÷份数。",
    "t": "10秒"
  },
  {
    "id": "D_S8_002",
    "type": "口算",
    "chapter": 8,
    "kp": "平均数",
    "diff": "基础",
    "q": "一组数据为：5,9,8,6,7，平均数是____。",
    "ans": "7",
    "exp": "(5+9+8+6+7)÷5=35÷5=7。",
    "t": "20秒"
  },
  {
    "id": "D_S8_003",
    "type": "口算",
    "chapter": 8,
    "kp": "平均数",
    "diff": "基础",
    "q": "小明3次数学测验分别为85分、92分、93分，平均分是____。",
    "ans": "90分",
    "exp": "(85+92+93)÷3=270÷3=90。",
    "t": "20秒"
  },
  {
    "id": "D_S8_004",
    "type": "选择题",
    "chapter": 8,
    "kp": "平均数",
    "diff": "基础",
    "q": "平均数（ ）这一组数据中的最大值。",
    "opts": [
      "A.大于",
      "B.小于",
      "C.不大于",
      "D.无法确定"
    ],
    "ans": "C",
    "exp": "平均数一定不大于最大值，也不小于最小值。",
    "t": "15秒"
  },
  {
    "id": "D_S8_005",
    "type": "填空题",
    "chapter": 8,
    "kp": "平均数",
    "diff": "中等",
    "q": "4个同学的身高分别为140cm、145cm、148cm、143cm，他们的平均身高是____cm。",
    "ans": "144",
    "exp": "(140+145+148+143)÷4=576÷4=144。",
    "t": "20秒"
  },
  {
    "id": "D_S8_006",
    "type": "应用题",
    "chapter": 8,
    "kp": "平均数",
    "diff": "中等",
    "q": "一辆汽车前2小时行驶了140千米，后3小时行驶了220千米。这辆汽车平均每小时行驶多少千米？",
    "ans": "72千米/时",
    "exp": "(140+220)÷(2+3)=360÷5=72。",
    "t": "25秒"
  },
  {
    "id": "D_S8_007",
    "type": "口算",
    "chapter": 8,
    "kp": "平均数",
    "diff": "基础",
    "q": "5个数的平均数是12，这5个数的总和是____。",
    "ans": "60",
    "exp": "总数=平均数×份数=12×5=60。",
    "t": "15秒"
  },
  {
    "id": "D_S8_008",
    "type": "应用题",
    "chapter": 8,
    "kp": "平均数",
    "diff": "中等",
    "q": "小红读一本书，前3天共读96页，后4天每天读20页，这周平均每天读多少页？",
    "ans": "25页",
    "exp": "总页数=96+4x20=176页，总天数=7天，平均=176/7=25页。",
    "t": "30秒"
  },
  {
    "id": "D_S8_009",
    "type": "口算",
    "chapter": 8,
    "kp": "平均数",
    "diff": "中等",
    "q": "4个数的平均数是15，如果再加上一个数5，现在5个数的平均数是____。",
    "ans": "13",
    "exp": "4×15=60, 60+5=65, 65÷5=13。",
    "t": "20秒"
  },
  {
    "id": "D_S8_010",
    "type": "填空题",
    "chapter": 8,
    "kp": "复式条形统计图",
    "diff": "基础",
    "q": "在复式条形统计图中，通常用____种不同颜色来区分不同类别的数据，并配有____。",
    "ans": "两；图例",
    "exp": "复式条形图用图例区分两组数据。",
    "t": "15秒"
  },
  {
    "id": "D_S8_011",
    "type": "选择题",
    "chapter": 8,
    "kp": "平均数",
    "diff": "中等",
    "q": "小明期中考试语文、数学、英语平均分是88分，已知语文86分，数学90分，英语是多少分？",
    "opts": [
      "A.86",
      "B.88",
      "C.90",
      "D.92"
    ],
    "ans": "B",
    "exp": "88×3=264, 264-86-90=88。",
    "t": "20秒"
  },
  {
    "id": "D_S8_012",
    "type": "口算",
    "chapter": 8,
    "kp": "平均数",
    "diff": "基础",
    "q": "数据8、9、7、10、11的平均数是____。",
    "ans": "9",
    "exp": "(8+9+7+10+11)÷5=45÷5=9。",
    "t": "15秒"
  },
  {
    "id": "D_S8_013",
    "type": "应用题",
    "chapter": 8,
    "kp": "平均数",
    "diff": "提高",
    "q": "有7个数的平均数是20，前三个数的平均数是18，后五个数的平均数是22，第三个数是多少？",
    "ans": "28",
    "exp": "7数和=140，前3数和=54，后5数和=110。前3+后5=164，第三个数被多算一次。164-140=24...修正思路：设第三个数为x，前3+(后5)多算了x一次，54+110-x=140, x=24。",
    "t": "50秒"
  },
  {
    "id": "D_S8_014",
    "type": "应用题",
    "chapter": 8,
    "kp": "平均数",
    "diff": "提高",
    "q": "甲、乙、丙三个数的平均数是150，甲是120，乙和丙相等。乙是多少？",
    "ans": "165",
    "exp": "三数和=450，乙+丙=450-120=330，乙=330÷2=165。",
    "t": "25秒"
  },
  {
    "id": "D_S8_015",
    "type": "口算",
    "chapter": 8,
    "kp": "平均数",
    "diff": "基础",
    "q": "体育课上，5名同学跳绳个数：120,115,125,118,122，平均每人跳____个。",
    "ans": "120",
    "exp": "(120+115+125+118+122)÷5=600÷5=120。",
    "t": "20秒"
  },
  {
    "id": "D_S8_016",
    "type": "应用题",
    "chapter": 8,
    "kp": "平均数",
    "diff": "中等",
    "q": "一辆车从甲地到乙地，前3小时每小时行70千米，后2小时每小时行80千米，这辆车平均每小时行多少千米？",
    "ans": "74千米/时",
    "exp": "总路程=3×70+2×80=210+160=370，总时间=5小时，平均=370÷5=74。",
    "t": "25秒"
  },
  {
    "id": "D_S8_017",
    "type": "填空题",
    "chapter": 8,
    "kp": "复式条形统计图",
    "diff": "基础",
    "q": "复式条形统计图优点是不仅可以看出____的多少，还能____两组数据。",
    "ans": "数量；比较",
    "exp": "复式条形图便于直接比较。",
    "t": "15秒"
  },
  {
    "id": "D_S8_018",
    "type": "口算",
    "chapter": 8,
    "kp": "平均数",
    "diff": "中等",
    "q": "如果一组数据的平均数是25，增加一个数据后平均数变成了28，新增的数据可能是____（大于或小于25）。",
    "ans": "大于",
    "exp": "平均数增大说明新增数据大于原平均数。",
    "t": "15秒"
  },
  {
    "id": "D_S8_019",
    "type": "选择题",
    "chapter": 8,
    "kp": "平均数",
    "diff": "基础",
    "q": "下面关于平均数的说法，（ ）是错误的。",
    "opts": [
      "A.平均数在最大和最小值之间",
      "B.平均数是一组数据的平均值",
      "C.平均数就是中间的数",
      "D.平均数可以用来代表一组数据的总体水平"
    ],
    "ans": "C",
    "exp": "平均数不是中间的数（中间的数叫中位数）。",
    "t": "15秒"
  },
  {
    "id": "D_S8_020",
    "type": "应用题",
    "chapter": 8,
    "kp": "平均数",
    "diff": "提高",
    "q": "有5个数，平均数是15。如果把其中一个数改为10，平均数变成12，被改动的数原是多少？",
    "ans": "25",
    "exp": "原总和=75，新总和=60，新比旧少15。所以被改动的数=10+15=25。",
    "t": "30秒"
  }
]